pptx2typ/__init__.py
pptx2typ/cli.py
pptx2typ-0.1.1.dist-info/LICENSE
pptx2typ-0.1.1.dist-info/METADATA
pptx2typ-0.1.1.dist-info/WHEEL
pptx2typ-0.1.1.dist-info/entry_points.txt
pptx2typ-0.1.1.dist-info/top_level.txt
pptx2typ-0.1.1.dist-info/RECORD
