Metadata-Version: 2.1
Name: pptx2typ
Version: 0.1.1
Summary: A tool to convert PPTX files to Typst Touying scripts.
Author-email: Sizhe Liu <sizhe.liu@fit-foxconn.com>
License: MIT
Requires-Python: >=3.7
License-File: LICENSE
Requires-Dist: click==8.1.7
Requires-Dist: Jinja2==3.1.4
Requires-Dist: lxml==5.3.0
Requires-Dist: markdown-it-py==3.0.0
Requires-Dist: MarkupSafe==3.0.1
Requires-Dist: mdurl==0.1.2
Requires-Dist: packaging==24.1
Requires-Dist: pdf2image==1.17.0
Requires-Dist: pillow==10.4.0
Requires-Dist: pip==22.0.2
Requires-Dist: Pygments==2.18.0
Requires-Dist: pyproject-hooks==1.2.0
Requires-Dist: python-pptx==1.0.2
Requires-Dist: RapidFuzz==3.10.0
Requires-Dist: rich==13.9.2
Requires-Dist: setuptools==59.6.0
Requires-Dist: shellingham==1.5.4
Requires-Dist: tomli==2.0.2
Requires-Dist: typing-extensions==4.12.2
Requires-Dist: XlsxWriter==3.2.0
